{"周一": [{"anime_name": "异度侵入（ID:INVADED）", "weekday": "周一", "play_time": "00:30", "play_date": "1.6", "play_nums": "13", "tags": ["悬疑", "科幻", "剧情向"]}, {"anime_name": "别对映像研出手！", "weekday": "周一", "play_time": "01:00", "play_date": "1.6", "play_nums": "12", "tags": ["校园", "青春", "动画制作"]}, {"anime_name": "房间露营△", "weekday": "周一", "play_time": "20:55", "play_date": "1.6", "play_nums": "12", "tags": ["日常", "轻百合"]}, {"anime_name": "ARP Backstage Pass", "weekday": "周一", "play_time": "22:00", "play_date": "1.13", "play_nums": "11", "tags": ["音乐", "偶像男团", "AR技术"]}, {"anime_name": "梦幻之星 神谕篇", "weekday": "周一", "play_time": "23:00", "play_date": "连载中", "play_nums": "25", "tags": ["战斗", "科幻"]}, {"anime_name": "成群逐队！西顿学园", "weekday": "周一", "play_time": "23:30", "play_date": "1.6", "play_nums": "12", "tags": ["校园", "搞笑", "兽娘", "恋爱", "后宫"]}], "周三": [{"anime_name": "魔术士欧菲流浪之旅", "weekday": "周三", "play_time": "01:00", "play_date": "1.8", "play_nums": "13", "tags": ["奇幻", "冒险", "战斗", "有生之年"]}, {"anime_name": "花牌情缘 第三季", "weekday": "周三", "play_time": "02:29", "play_date": "连载中", "play_nums": "24", "tags": ["青春", "竞技", "乙女向"]}, {"anime_name": "草裙舞女孩 petit", "weekday": "周三", "play_time": "06:30", "play_date": "1.8", "play_nums": "", "tags": []}, {"anime_name": "七大罪 诸神的逆鳞", "weekday": "周三", "play_time": "18:00", "play_date": "连载中", "play_nums": "24", "tags": ["热血", "奇幻", "战斗", "神魔"]}, {"anime_name": "篮球少年王（鸭子的天空）", "weekday": "周三", "play_time": "18:25", "play_date": "连载中", "play_nums": "50", "tags": ["运动", "篮球", "热血", "励志", "竞技"]}, {"anime_name": "虚空魔境 第二季", "weekday": "周三", "play_time": "19:30", "play_date": "连载中", "play_nums": "21", "tags": ["热血", "奇幻", "战斗", "日法合作"]}, {"anime_name": "number24", "weekday": "周三", "play_time": "21:30", "play_date": "1.8", "play_nums": "12", "tags": ["运动", "青春", "橄榄球"]}, {"anime_name": "因为太怕痛就全点防御力了", "weekday": "周三", "play_time": "22:30", "play_date": "1.8", "play_nums": "12", "tags": ["网游", "盾娘", "搞笑", "风傲天"]}, {"anime_name": "Re:从零开始的异世界生活 新编集版", "weekday": "周三", "play_time": "23:30", "play_date": "1.1", "play_nums": "13", "tags": ["穿越", "奇幻", "战斗", "轮回", "重置"]}], "周二": [{"anime_name": "A3!满开剧团 春&夏", "weekday": "周二", "play_time": "00:30", "play_date": "1.14", "play_nums": "12", "tags": ["偶像", "剧团", "乙女向"]}, {"anime_name": "缘结熊本", "weekday": "周二", "play_time": "00:35", "play_date": "1.7", "play_nums": "12", "tags": []}, {"anime_name": "BREAKERS", "weekday": "周二", "play_time": "17:45", "play_date": "1.7", "play_nums": "16", "tags": ["运动", "励志"]}, {"anime_name": "黑色四叶草（黑色五叶草）", "weekday": "周二", "play_time": "18:25", "play_date": "连载中", "play_nums": "", "tags": ["奇幻", "魔法", "热血", "战斗", "咆哮帝"]}, {"anime_name": "钻石王牌 actⅡ", "weekday": "周二", "play_time": "18:30", "play_date": "连载中", "play_nums": "52", "tags": ["热血", "竞技", "棒球", "运动"]}, {"anime_name": "BanG Dream! 梦想协奏曲 第三季", "weekday": "周二", "play_time": "19:00", "play_date": "1.7", "play_nums": "13", "tags": ["音乐", "偶像", "邦邦", "轻百合"]}, {"anime_name": "异世界四重奏 第二季", "weekday": "周二", "play_time": "23:30", "play_date": "1.14", "play_nums": "12", "tags": ["穿越", "搞笑", "校园", "五重奏(√)"]}], "周五": [{"anime_name": "宝石商人理查德的谜鉴定", "weekday": "周五", "play_time": "00:30", "play_date": "1.10", "play_nums": "12", "tags": ["悬疑", "推理", "美型"]}, {"anime_name": "家有圆圆？！～我家的圆圆你知道吗～", "weekday": "周五", "play_time": "01:40", "play_date": "1.10", "play_nums": "11", "tags": ["萌宠", "拟人化"]}, {"anime_name": "地缚少年花子君", "weekday": "周五", "play_time": "15:00", "play_date": "1.10", "play_nums": "12", "tags": ["奇幻", "恋爱", "狛里狛气", "北方栖姬"]}, {"anime_name": "神推偶像登上武道馆我就死而无憾", "weekday": "周五", "play_time": "15:30", "play_date": "1.10", "play_nums": "12", "tags": ["偶像宅", "恋慕", "轻百合"]}, {"anime_name": "恋爱小行星", "weekday": "周五", "play_time": "23:00", "play_date": "1.3", "play_nums": "12", "tags": ["日常", "天文地理", "轻百合", "芳文社"]}], "周六": [{"anime_name": "某科学的超电磁炮 第三季", "weekday": "周六", "play_time": "00:05", "play_date": "1.11", "play_nums": "25", "tags": ["科幻", "校园", "战斗", "轻百合", "哔哩哔哩"]}, {"anime_name": "达尔文游戏", "weekday": "周六", "play_time": "00:30", "play_date": "1.4", "play_nums": "11", "tags": ["科幻", "战斗", "生存", "“吃鸡”"]}, {"anime_name": "歌舞伎町夏洛克", "weekday": "周六", "play_time": "00:55", "play_date": "连载中", "play_nums": "24", "tags": ["悬疑", "群像"]}, {"anime_name": "织田肉桂信长", "weekday": "周六", "play_time": "01:23", "play_date": "1.11", "play_nums": "12", "tags": ["萌宠", "搞笑", "转生", "日常"]}, {"anime_name": "排球少年 第四季", "weekday": "周六", "play_time": "01:30", "play_date": "1.11", "play_nums": "季", "tags": ["运动", "热血", "青春", "竞技"]}, {"anime_name": "请在T台上微笑", "weekday": "周六", "play_time": "02:55", "play_date": "1.11", "play_nums": "12", "tags": ["模特", "时装", "青春", "励志"]}, {"anime_name": "偶像活动 on Parade！", "weekday": "周六", "play_time": "10:30", "play_date": "连载中", "play_nums": "25", "tags": []}, {"anime_name": "我的英雄学院 第四季", "weekday": "周六", "play_time": "18:00", "play_date": "连载中", "play_nums": "25", "tags": ["热血", "战斗", "超能力", "校园", "励志"]}, {"anime_name": "入间同学入魔了", "weekday": "周六", "play_time": "19:00", "play_date": "连载中", "play_nums": "23", "tags": ["奇幻", "搞笑", "校园"]}, {"anime_name": "暗黑破坏神在身边", "weekday": "周六", "play_time": "20:00", "play_date": "1.11", "play_nums": "12", "tags": ["校园", "中二", "日常", "吐槽", "不要过来啊"]}, {"anime_name": "异种族风俗娘评鉴指南", "weekday": "周六", "play_time": "22:30", "play_date": "1.11", "play_nums": "12", "tags": ["魔物娘", "奇幻", "搞笑", "肉", "网盘见"]}, {"anime_name": "平安达纪", "weekday": "周六", "play_time": "22:57", "play_date": "1.4", "play_nums": "", "tags": []}, {"anime_name": "22/7", "weekday": "周六", "play_time": "23:30", "play_date": "1.11", "play_nums": "12", "tags": ["偶像", "音乐"]}], "周四": [{"anime_name": "星掠者", "weekday": "周四", "play_time": "01:05", "play_date": "1.9", "play_nums": "24", "tags": ["奇幻", "战斗", "爽片", "杀必死"]}, {"anime_name": "猫娘乐园（NEKOPARA）", "weekday": "周四", "play_time": "22:00", "play_date": "1.9", "play_nums": "12", "tags": ["萌系", "猫娘", "后宫", "“艹猫”"]}, {"anime_name": "SHOW BY ROCK!! 第三季", "weekday": "周四", "play_time": "22:30", "play_date": "1.9", "play_nums": "12", "tags": ["音乐", "兽耳", "萌系", "轻百合"]}, {"anime_name": "奇幻☆怪盗", "weekday": "周四", "play_time": "22:30", "play_date": "1.9", "play_nums": "", "tags": ["奇幻", "怪盗", "恋爱"]}, {"anime_name": "索玛丽与森林之神", "weekday": "周四", "play_time": "23:00", "play_date": "1.2", "play_nums": "12", "tags": ["奇幻", "亲情", "泣向", "末世"]}, {"anime_name": "无限系统树", "weekday": "周四", "play_time": "23:00", "play_date": "1.9", "play_nums": "13", "tags": ["科幻", "网游", "战斗"]}, {"anime_name": "无限之住人-IMMORTAL-", "weekday": "周四", "play_time": "23:00", "play_date": "连载中", "play_nums": "24", "tags": ["武士", "打斗", "重置"]}], "周日": [{"anime_name": "命运-冠位指定 绝对魔兽战线 巴比伦尼亚", "weekday": "周日", "play_time": "00:00", "play_date": "连载中", "play_nums": "21", "tags": ["战斗", "奇幻", "冒险"]}, {"anime_name": "魔法纪录 魔法少女小圆外传", "weekday": "周日", "play_time": "00:30", "play_date": "1.5", "play_nums": "13", "tags": ["奇幻", "打斗", "马猴烧酒", "致郁"]}, {"anime_name": "虚构推理", "weekday": "周日", "play_time": "02:00", "play_date": "1.12", "play_nums": "12", "tags": ["悬疑", "口胡推理", "狗粮", "奇幻", "骚话"]}, {"anime_name": "Healin' Good ♡ 光之美少女", "weekday": "周日", "play_time": "12:00", "play_date": "2.2", "play_nums": "", "tags": ["奇幻", "战斗", "魔法少女"]}, {"anime_name": "咯咯咯鬼太郎 第六季", "weekday": "周日", "play_time": "12:00", "play_date": "连载中", "play_nums": "", "tags": ["妖怪", "冒险", "悬疑", "经典"]}, {"anime_name": "博人传 火影忍者新时代", "weekday": "周日", "play_time": "17:30", "play_date": "连载中", "play_nums": "", "tags": ["热血", "战斗", "冒险", "忍者世界"]}, {"anime_name": "ReBIRTH", "weekday": "周日", "play_time": "20:30", "play_date": "1.5", "play_nums": "", "tags": []}, {"anime_name": "八十龟酱观察日记 第二季", "weekday": "周日", "play_time": "20:54", "play_date": "1.5", "play_nums": "12", "tags": ["日常", "搞笑"]}, {"anime_name": "思维覆写（pet）", "weekday": "周日", "play_time": "23:00", "play_date": "1.5", "play_nums": "13", "tags": ["奇幻", "超能力", "黑社会", "烧脑"]}, {"anime_name": "OVERFLOW", "weekday": "周日", "play_time": "23:00", "play_date": "1.5", "play_nums": "8", "tags": ["福利", "“鼓掌”", "网盘见"]}, {"anime_name": "异兽魔都", "weekday": "周日", "play_time": "23:00", "play_date": "1.12", "play_nums": "12", "tags": ["奇幻", "暴力", "黑色幽默", "幻想"]}]}