{
  "周一": [
    {
      "anime_name": "社长，战斗时间到！",
      "weekday": "周一",
      "cover_url": "https://unmc.cdn.bcebos.com/1695451776017_1881611763.jpg",
      "cover_url_git": "img/2020/04/社长，战斗时间到！.jpg",
      "play_time": "00:00",
      "play_date": "4.6",
      "play_nums": "12",
      "tags": ["奇幻", "冒险", "战斗"]
    },
    {
      "anime_name": "王者天下 第三季",
      "weekday": "周一",
      "cover_url": "https://pic.rmb.bdstatic.com/bjh/down/bc658f5eb6c52f1ed70992a79c26ad7f.jpeg",
      "cover_url_git": "img/2020/04/王者天下 第三季.jpeg",
      "play_time": "02:45",
      "play_date": "4.6",
      "play_nums": "26",
      "tags": ["热血", "战争", "历史"]
    },
    {
      "anime_name": "女学。～圣女斯克威尔学院～",
      "weekday": "周一",
      "cover_url": "https://cdn.yinghuazy.xyz/upload/vod/20210222-1/d34d076fe159012b23d8587072365288.jpg",
      "cover_url_git": "img/2020/04/女学。～圣女斯克威尔学院～.jpg",
      "play_time": "07:05",
      "play_date": "4.6",
      "play_nums": "50",
      "tags": ["日常", "萌系", "校园", "偶像"]
    },
    {
      "anime_name": "别册奥林匹克之环",
      "weekday": "周一",
      "cover_url": "https://pic.rmb.bdstatic.com/bjh/down/ad09b85f62b84256df8740cb000b8e62.jpeg",
      "cover_url_git": "img/2020/04/别册奥林匹克之环.jpeg",
      "play_time": "22:00",
      "play_date": "4.20",
      "play_nums": "24",
      "tags": ["体育运动", "穿越", "定格动画"]
    },
    {
      "anime_name": "胖腹动物的生活",
      "weekday": "周一",
      "cover_url": "https://cdn.yinghuazy.xyz/upload/vod/20201029-1/74e4b1bb8a10d19cb7e6133599036a5e.jpg",
      "cover_url_git": "img/2020/04/胖腹动物的生活.jpg",
      "play_time": "22:29",
      "play_date": "4.6",
      "play_nums": "50",
      "tags": ["搞笑", "动物拟人"]
    },
    {
      "anime_name": "公主连结！Re:Dive",
      "weekday": "周一",
      "cover_url": "https://pic.rmb.bdstatic.com/bjh/down/82f7eb94196eead61200f08dee5bd33f.jpeg",
      "cover_url_git": "img/2020/04/公主连结！Re:Dive.jpeg",
      "play_time": "23:00",
      "play_date": "4.6",
      "play_nums": "13",
      "tags": ["奇幻", "冒险", "战斗", "轻百合", "“接头霸王”"]
    },
    {
      "anime_name": "白猫计划",
      "weekday": "周一",
      "cover_url": "https://unmc.cdn.bcebos.com/1695369905455_1869344835.jpg",
      "cover_url_git": "img/2020/04/白猫计划.jpg",
      "play_time": "23:00",
      "play_date": "4.6",
      "play_nums": "12",
      "tags": ["奇幻", "冒险", "战斗", "恋爱"]
    },
    {
      "anime_name": "啄木鸟侦探社",
      "weekday": "周一",
      "cover_url": "https://pic.rmb.bdstatic.com/bjh/down/79dd0f61d09234dc02d32830616f814c.jpeg",
      "cover_url_git": "img/2020/04/啄木鸟侦探社.jpeg",
      "play_time": "23:30",
      "play_date": "4.13",
      "play_nums": "12",
      "tags": ["文豪", "悬疑", "推理"]
    }
  ],
  "周二": [
    {
      "anime_name": "那个世界属于妖怪组",
      "weekday": "周二",
      "cover_url": "https://cdn.aqdstatic.com:966/age/20180281.jpg",
      "cover_url_git": "img/2020/04/那个世界属于妖怪组.jpg",
      "play_time": "00:00",
      "play_date": "4.7",
      "play_nums": "",
      "tags": ["搞笑", "奇幻"]
    },
    {
      "anime_name": "A3!满开剧团 春&夏",
      "weekday": "周二",
      "cover_url": "https://cdn.yinghuazy.xyz/upload/vod/20201216-1/7c80419dd9eff605697f14fb7d6ac59b.jpg",
      "cover_url_git": "img/2020/04/A3!满开剧团 春&夏.jpg",
      "play_time": "00:30",
      "play_date": "4.28",
      "play_nums": "12",
      "tags": ["偶像", "音乐", "剧团", "乙女向"]
    },
    {
      "anime_name": "水果篮子 第二季（新作）",
      "weekday": "周二",
      "cover_url": "https://pic.rmb.bdstatic.com/bjh/down/79f1b1d1d9683cb11098ddde97fa34ea.jpeg",
      "cover_url_git": "img/2020/04/水果篮子 第二季（新作）.jpeg",
      "play_time": "01:30",
      "play_date": "4.7",
      "play_nums": "25",
      "tags": ["奇幻", "校园", "恋爱", "治愈", "乙女向"]
    },
    {
      "anime_name": "影之诗",
      "weekday": "周二",
      "cover_url": "https://pic.rmb.bdstatic.com/bjh/down/2c4a491783ce3ee40160e30c7060d542.jpeg",
      "cover_url_git": "img/2020/04/影之诗.jpeg",
      "play_time": "17:55",
      "play_date": "4.7",
      "play_nums": "48",
      "tags": ["卡牌", "竞技", "“真游戏王”"]
    },
    {
      "anime_name": "黑色四叶草（黑色五叶草）",
      "weekday": "周二",
      "cover_url": "https://dm530.org/thumbnails/6738.jpg",
      "cover_url_git": "img/2020/04/黑色四叶草（黑色五叶草）.jpg",
      "play_time": "18:25",
      "play_date": "连载中",
      "play_nums": "",
      "tags": ["奇幻", "魔法", "热血", "战斗", "咆哮帝"]
    },
    {
      "anime_name": "放学后海堤日记",
      "weekday": "周二",
      "cover_url": "https://cdn.yinghuazy.xyz/upload/vod/20201029-5/06bbc79cf561f7d5e5dbef0b06b5236d.jpg",
      "cover_url_git": "img/2020/04/放学后海堤日记.jpg",
      "play_time": "22:30",
      "play_date": "4.7",
      "play_nums": "12",
      "tags": ["日常", "搞笑", "钓鱼"]
    }
  ],
  "周三": [
    {
      "anime_name": "篮球少年王（鸭子的天空）",
      "weekday": "周三",
      "cover_url": "https://unmc.cdn.bcebos.com/1695891288805_356135127.jpg",
      "cover_url_git": "img/2020/04/篮球少年王（鸭子的天空）.jpg",
      "play_time": "18:25",
      "play_date": "连载中",
      "play_nums": "50",
      "tags": ["运动", "篮球", "热血", "励志", "竞技"]
    },
    {
      "anime_name": "球咏",
      "weekday": "周三",
      "cover_url": "https://cdn.yinghuazy.xyz/upload/vod/20201029-5/096fb9896975977fc64b262e8e16e099.jpg",
      "cover_url_git": "img/2020/04/球咏.jpg",
      "play_time": "22:00",
      "play_date": "4.1",
      "play_nums": "12",
      "tags": ["运动", "棒球", "校园", "轻百合", "芳文社"]
    },
    {
      "anime_name": "神之塔",
      "weekday": "周三",
      "cover_url": "https://dm530.org/thumbnails/21788.jpg",
      "cover_url_git": "img/2020/04/神之塔.jpg",
      "play_time": "23:30",
      "play_date": "4.1",
      "play_nums": "13",
      "tags": ["奇幻", "冒险", "战斗"]
    }
  ],
  "周四": [
    {
      "anime_name": "星掠者",
      "weekday": "周四",
      "cover_url": "https://cdn.yinghuazy.xyz/upload/vod/20201029-4/7f51aad17beffb36e41105606a7dc066.jpg",
      "cover_url_git": "img/2020/04/星掠者.jpg",
      "play_time": "01:05",
      "play_date": "连载中",
      "play_nums": "24",
      "tags": ["奇幻", "战斗", "冒险", "肉"]
    },
    {
      "anime_name": "高达创形者 再起 第二季",
      "weekday": "周四",
      "cover_url": "https://cdn.yinghuazy.xyz/upload/vod/20201029-2/82221bb6b30a66436c2a80e71ea39ff1.jpg",
      "cover_url_git": "img/2020/04/高达创形者 再起 第二季.jpg",
      "play_time": "19:00",
      "play_date": "4.9",
      "play_nums": "",
      "tags": ["机战", "科幻", "热血", "卖胶"]
    },
    {
      "anime_name": "八男？别闹了！",
      "weekday": "周四",
      "cover_url": "https://dm530.org/thumbnails/21553.jpg",
      "cover_url_git": "img/2020/04/八男？别闹了！.jpg",
      "play_time": "20:00",
      "play_date": "4.2",
      "play_nums": "12",
      "tags": ["穿越", "奇幻", "冒险", "后宫", "龙傲天"]
    },
    {
      "anime_name": "隐瞒之事",
      "weekday": "周四",
      "cover_url": "https://cdn.yinghuazy.xyz/upload/vod/20201029-5/7443200436f366bac922190ca9e4b3b9.jpg",
      "cover_url_git": "img/2020/04/隐瞒之事.jpg",
      "play_time": "23:45",
      "play_date": "4.2",
      "play_nums": "12",
      "tags": ["搞笑", "日常", "父女", "治愈"]
    }
  ],
  "周五": [
    {
      "anime_name": "富豪刑事 Balance:UNLIMITED",
      "weekday": "周五",
      "cover_url": "https://pic.rmb.bdstatic.com/bjh/down/566bbe62a5ae1a615a36d686be5b1928.jpeg",
      "cover_url_git": "img/2020/04/富豪刑事 Balance:UNLIMITED.jpeg",
      "play_time": "01:10",
      "play_date": "4.10",
      "play_nums": "11",
      "tags": ["悬疑", "侦探", "钞能力"]
    },
    {
      "anime_name": "座敷童子榻榻米酱",
      "weekday": "周五",
      "cover_url": "https://cdn.yinghuazy.xyz/upload/vod/20201216-1/ab27db94c66a909d3aab19c1f4e9c045.jpg",
      "cover_url_git": "img/2020/04/座敷童子榻榻米酱.jpg",
      "play_time": "19:30",
      "play_date": "4.10",
      "play_nums": "12",
      "tags": ["奇幻", "搞笑", "鬼魂"]
    },
    {
      "anime_name": "天晴烂漫！",
      "weekday": "周五",
      "cover_url": "https://cdn.yinghuazy.xyz/upload/vod/20201029-5/9c61a45fb82768c9010fcda8c10e5cd5.jpg",
      "cover_url_git": "img/2020/04/天晴烂漫！.jpg",
      "play_time": "21:30",
      "play_date": "4.10",
      "play_nums": "",
      "tags": ["竞技", "汽车", "19世纪美国"]
    },
    {
      "anime_name": "新樱花大战",
      "weekday": "周五",
      "cover_url": "https://dm530.org/thumbnails/21701.jpg",
      "cover_url_git": "img/2020/04/新樱花大战.jpg",
      "play_time": "22:00",
      "play_date": "4.3",
      "play_nums": "12",
      "tags": ["机战", "大正"]
    }
  ],
  "周六": [
    {
      "anime_name": "某科学的超电磁炮 第三季",
      "weekday": "周六",
      "cover_url": "https://dm530.org/thumbnails/21479.jpg",
      "cover_url_git": "img/2020/04/某科学的超电磁炮 第三季.jpg",
      "play_time": "00:05",
      "play_date": "连载中",
      "play_nums": "25",
      "tags": ["科幻", "校园", "战斗", "轻百合", "哔哩哔哩"]
    },
    {
      "anime_name": "食戟之灵 第五季",
      "weekday": "周六",
      "cover_url": "https://cdn.aqdstatic.com:966/age/20200143.jpg",
      "cover_url_git": "img/2020/04/食戟之灵 第五季.jpg",
      "play_time": "00:30",
      "play_date": "4.11",
      "play_nums": "13",
      "tags": ["美食", "竞技", "校园", "热血"]
    },
    {
      "anime_name": "文豪与炼金术师 ～审判的齿轮～",
      "weekday": "周六",
      "cover_url": "https://unmc.cdn.bcebos.com/1695369744027_425117858.jpg",
      "cover_url_git": "img/2020/04/文豪与炼金术师 ～审判的齿轮～.jpg",
      "play_time": "01:23",
      "play_date": "4.4",
      "play_nums": "13",
      "tags": ["文豪", "战斗", "奇幻", "架空"]
    },
    {
      "anime_name": "ARGONAVIS from BanG Dream!",
      "weekday": "周六",
      "cover_url": "https://pic.rmb.bdstatic.com/bjh/down/87d61073771d37c71a0fd7d717c38e9f.jpeg",
      "cover_url_git": "img/2020/04/ARGONAVIS from BanG Dream!.jpeg",
      "play_time": "02:00",
      "play_date": "4.11",
      "play_nums": "季",
      "tags": ["偶像", "音乐", "乐队", "励志"]
    },
    {
      "anime_name": "聆听者（LISTENERS）",
      "weekday": "周六",
      "cover_url": "https://cdn.yinghuazy.xyz/upload/vod/20201029-5/a16e0ce22916573eadb0cd975bf79c6d.jpg",
      "cover_url_git": "img/2020/04/聆听者（LISTENERS）.jpg",
      "play_time": "02:10",
      "play_date": "4.4",
      "play_nums": "12",
      "tags": ["科幻", "音乐", "机战"]
    },
    {
      "anime_name": "听我的电波吧",
      "weekday": "周六",
      "cover_url": "https://cdn.yinghuazy.xyz/upload/vod/20201029-5/987b44010fbe1c9c0fa3b4efaaab957b.jpg",
      "cover_url_git": "img/2020/04/听我的电波吧.jpg",
      "play_time": "02:25",
      "play_date": "4.4",
      "play_nums": "12",
      "tags": ["搞笑", "职场", "励志"]
    },
    {
      "anime_name": "棒球大联盟2nd 第二季",
      "weekday": "周六",
      "cover_url": "https://pic.rmb.bdstatic.com/bjh/down/98d4dccabf99127e1bc71e70d3a6608c.jpeg",
      "cover_url_git": "img/2020/04/棒球大联盟2nd 第二季.jpeg",
      "play_time": "16:35",
      "play_date": "4.4",
      "play_nums": "",
      "tags": ["运动", "棒球", "竞技"]
    },
    {
      "anime_name": "喷嚏大魔王2020",
      "weekday": "周六",
      "cover_url": "https://dm530.org/thumbnails/35040448.jpg",
      "cover_url_git": "img/2020/04/喷嚏大魔王2020.jpg",
      "play_time": "18:00",
      "play_date": "4.11",
      "play_nums": "",
      "tags": ["奇幻", "搞笑", "冒险"]
    },
    {
      "anime_name": "阿尔蒂（ARTE）",
      "weekday": "周六",
      "cover_url": "https://pic.rmb.bdstatic.com/bjh/down/03bf3472123e3df5ab0b1e24209e9f9a.jpeg",
      "cover_url_git": "img/2020/04/阿尔蒂（ARTE）.jpeg",
      "play_time": "22:30",
      "play_date": "4.4",
      "play_nums": "12",
      "tags": ["艺术", "励志", "文艺复兴"]
    }
  ],
  "周日": [
    {
      "anime_name": "辉夜大小姐想让我告白 第二季",
      "weekday": "周日",
      "cover_url": "https://dm530.org/thumbnails/21709.jpg",
      "cover_url_git": "img/2020/04/辉夜大小姐想让我告白 第二季.jpg",
      "play_time": "00:00",
      "play_date": "4.12",
      "play_nums": "12",
      "tags": ["恋爱", "搞笑", "校园", "日常", "智斗", "狗粮"]
    },
    {
      "anime_name": "昨日之歌",
      "weekday": "周日",
      "cover_url": "https://cdn.yinghuazy.xyz/upload/vod/20201029-5/f2b2b6f1e3b1e18e433fed032d15ed5a.jpg",
      "cover_url_git": "img/2020/04/昨日之歌.jpg",
      "play_time": "00:30",
      "play_date": "4.5",
      "play_nums": "12+6",
      "tags": ["恋爱", "青春", "胃疼"]
    },
    {
      "anime_name": "辣妹与恐龙",
      "weekday": "周日",
      "cover_url": "https://unmc.cdn.bcebos.com/1695369883100_284310814.jpg",
      "cover_url_git": "img/2020/04/辣妹与恐龙.jpg",
      "play_time": "01:30",
      "play_date": "4.5",
      "play_nums": "12",
      "tags": ["搞笑", "日常"]
    },
    {
      "anime_name": "转生成为了只有乙女游戏破灭Flag的邪恶大小姐",
      "weekday": "周日",
      "cover_url": "https://cdn.yinghuazy.xyz/upload/vod/20210319-1/852d8b247f977ac48c9d3e0699de5fc5.jpg",
      "cover_url_git": "img/2020/04/转生成为了只有乙女游戏破灭Flag的邪恶大小姐.jpg",
      "play_time": "02:00",
      "play_date": "4.5",
      "play_nums": "12",
      "tags": ["奇幻", "穿越", "搞笑", "逆后宫", "乙女向"]
    },
    {
      "anime_name": "爱书的下克上：为了成为图书管理员不择手段！ 第二部",
      "weekday": "周日",
      "cover_url": "https://cdn.yinghuazy.xyz/upload/vod/20201029-4/895da1f071bf04516020e41df9feec29.jpg",
      "cover_url_git": "img/2020/04/爱书的下克上：为了成为图书管理员不择手段！ 第二部.jpg",
      "play_time": "02:10",
      "play_date": "4.5",
      "play_nums": "12",
      "tags": ["异世界", "奇幻", "日常", "种田", "励志"]
    },
    {
      "anime_name": "闪亮美妙☆频道 第三季",
      "weekday": "周日",
      "cover_url": "https://cdn.aqdstatic.com:966/age/20200187.jpg",
      "cover_url_git": "img/2020/04/闪亮美妙☆频道 第三季.jpg",
      "play_time": "10:00",
      "play_date": "4.5",
      "play_nums": "",
      "tags": ["偶像", "音乐"]
    },
    {
      "anime_name": "甜梦猫",
      "weekday": "周日",
      "cover_url": "https://unmc.cdn.bcebos.com/1695369347410_482492978.jpg",
      "cover_url_git": "img/2020/04/甜梦猫.jpg",
      "play_time": "10:30",
      "play_date": "4.5",
      "play_nums": "48",
      "tags": ["奇幻", "猫", "萌系", "治愈"]
    },
    {
      "anime_name": "Healin' Good ♡ 光之美少女",
      "weekday": "周日",
      "cover_url": "https://dm530.org/thumbnails/21768.jpg",
      "cover_url_git": "img/2020/04/Healin' Good ♡ 光之美少女.jpg",
      "play_time": "12:00",
      "play_date": "连载中",
      "play_nums": "",
      "tags": ["奇幻", "战斗", "魔法少女"]
    },
    {
      "anime_name": "数码兽大冒险：",
      "weekday": "周日",
      "cover_url": "https://dm530.org/thumbnails/21750.jpg",
      "cover_url_git": "img/2020/04/数码兽大冒险：.jpg",
      "play_time": "12:00",
      "play_date": "4.5",
      "play_nums": "年",
      "tags": ["科幻", "冒险", "战斗", "童年"]
    },
    {
      "anime_name": "博人传 火影忍者新时代",
      "weekday": "周日",
      "cover_url": "https://pic.rmb.bdstatic.com/bjh/down/089c8dce07fef34ee7f178a396933a5b.jpeg",
      "cover_url_git": "img/2020/04/博人传 火影忍者新时代.jpeg",
      "play_time": "17:30",
      "play_date": "连载中",
      "play_nums": "",
      "tags": ["热血", "战斗", "冒险", "忍者世界"]
    },
    {
      "anime_name": "更多！怪侠佐罗利",
      "weekday": "周日",
      "cover_url": "https://cdn.yinghuazy.xyz/upload/vod/20201029-3/6d0313a73a1277e8a274186602302b54.jpg",
      "cover_url_git": "img/2020/04/更多！怪侠佐罗利.jpg",
      "play_time": "18:00",
      "play_date": "4.5",
      "play_nums": "",
      "tags": ["冒险", "搞笑", "人外"]
    },
    {
      "anime_name": "IDOLiSH7-偶像星愿- 第二季",
      "weekday": "周日",
      "cover_url": "https://pic.rmb.bdstatic.com/bjh/down/fea4481d44b3186239110a0c31138989.jpeg",
      "cover_url_git": "img/2020/04/IDOLiSH7-偶像星愿- 第二季.jpeg",
      "play_time": "22:00",
      "play_date": "4.5",
      "play_nums": "15",
      "tags": ["偶像", "音乐", "励志"]
    },
    {
      "anime_name": "继 怪怪守护神（第二季）",
      "weekday": "周日",
      "cover_url": "https://dm530.org/thumbnails/21550.jpg",
      "cover_url_git": "img/2020/04/继 怪怪守护神（第二季）.jpg",
      "play_time": "22:30",
      "play_date": "4.5",
      "play_nums": "12",
      "tags": ["搞笑", "战斗", "后宫", "神魔", "肉"]
    },
    {
      "anime_name": "格莱普尼尔",
      "weekday": "周日",
      "cover_url": "https://cdn.aqdstatic.com:966/age/20200081.jpg",
      "cover_url_git": "img/2020/04/格莱普尼尔.jpg",
      "play_time": "22:30",
      "play_date": "4.5",
      "play_nums": "",
      "tags": ["奇幻", "战斗", "瑟气"]
    },
    {
      "anime_name": "用我的手指来扰乱吧。~在打烊后仅剩两人的沙龙…~",
      "weekday": "周日",
      "cover_url": "https://cdn.yinghuazy.xyz/upload/vod/20201207-1/5185d837e74074fbad6e1d1e7789c8ca.jpg",
      "cover_url_git": "img/2020/04/用我的手指来扰乱吧。~在打烊后仅剩两人的沙龙…~.jpg",
      "play_time": "23:00",
      "play_date": "4.5",
      "play_nums": "8",
      "tags": ["福利", "“鼓掌”", "网盘见"]
    }
  ]
}
